cs107_project/__init__.py
cs107_project/core_functionalities.py
cs107_project/cross_match.py
cs107_project/data_augmentation.py
cs107_project/machine_learning.py
cs107_project/visualization.py
cs107_project/visualization_interactive.py
cs107_team31_2023-0.0.1.dist-info/LICENSE
cs107_team31_2023-0.0.1.dist-info/METADATA
cs107_team31_2023-0.0.1.dist-info/WHEEL
cs107_team31_2023-0.0.1.dist-info/top_level.txt
cs107_team31_2023-0.0.1.dist-info/RECORD
