Metadata-Version: 2.1
Name: cs107-team31-2023
Version: 0.0.1
Summary: An API for interfacing with the Sloan Digital Sky Survey
Author-email: Austin Schwartz <aschwartz@college.harvard.edu>, Yilin Wang <yilin_wang@fas.harvard.edu>, Kejun Ying <kying@g.harvard.edu>, Azim Raheem <azimraheem@college.harvard.edu>, Zhengduan Du <zdu@g.harvard.edu>
Project-URL: Homepage, https://code.harvard.edu/CS107/team31_2023
Classifier: Programming Language :: Python :: 3
Classifier: License :: OSI Approved :: MIT License
Classifier: Operating System :: OS Independent
Requires-Python: >=3.7
License-File: LICENSE
Requires-Dist: pandas
Requires-Dist: numpy
Requires-Dist: astropy
Requires-Dist: astroML
Requires-Dist: astroquery
Requires-Dist: matplotlib
Requires-Dist: requests
Requires-Dist: scikit-learn
Requires-Dist: scipy
Requires-Dist: statsmodels
Requires-Dist: ipywidgets
